[
  {
    "role_name": "需求接收者",
    "skill_path": "roles/需求接收者/skill.md",
    "blocking_mode": "manual",
    "outputs": [
      {
        "name": "需求文档",
        "path": "00-需求描述.md"
      }
    ],
    "gate_rules": {
      "phase1_cross_validation": {
        "enabled": true
      },
      "phase2_schema_comparison": {
        "enabled": false
      },
      "phase3_anomaly_detection": {
        "enabled": false
      }
    },
    "input_groups": [
      [
        "需求接收者_校验_"
      ],
      [
        "需求接收者"
      ]
    ],
    "verdicts": [
      "confirmed"
    ]
  },
  {
    "role_name": "需求接收者（校验）",
    "skill_path": "roles/需求接收者_校验_/skill.md",
    "blocking_mode": "auto",
    "outputs": [
      {
        "name": "需求校验报告",
        "path": "outputs/需求接收者-validation.json"
      }
    ],
    "gate_rules": {
      "phase1_cross_validation": {
        "enabled": true
      },
      "phase2_schema_comparison": {
        "enabled": false
      },
      "phase3_anomaly_detection": {
        "enabled": false
      }
    },
    "inputs": [
      {
        "name": "需求文档",
        "path": "00-需求描述.md"
      }
    ],
    "input_groups": [
      [
        "需求接收者"
      ],
      [
        "需求接收者_校验_"
      ]
    ],
    "verdicts": [
      "confirmed",
      "loop"
    ]
  },
  {
    "role_name": "引擎分析师",
    "skill_path": "roles/引擎分析师/skill.md",
    "blocking_mode": "auto",
    "outputs": [
      {
        "name": "引擎分析报告",
        "path": "outputs/引擎分析报告.json"
      }
    ],
    "gate_rules": {
      "phase1_cross_validation": {
        "enabled": true
      },
      "phase2_schema_comparison": {
        "enabled": false
      },
      "phase3_anomaly_detection": {
        "enabled": false
      }
    },
    "inputs": [
      {
        "name": "需求文档",
        "path": "00-需求描述.md"
      },
      {
        "name": "SDK规范",
        "path": "knowledge/SDK_SPEC.md",
        "type": "knowledge"
      },
      {
        "name": "引擎特性提炼指南",
        "path": "knowledge/引擎特性提炼指南.md",
        "type": "knowledge"
      }
    ],
    "input_groups": [
      [
        "需求接收者_校验_"
      ],
      [
        "引擎分析师"
      ]
    ],
    "verdicts": [
      "confirmed"
    ]
  },
  {
    "role_name": "文档架构师",
    "skill_path": "roles/文档架构师/skill.md",
    "blocking_mode": "auto",
    "outputs": [
      {
        "name": "文档族架构设计",
        "path": "outputs/文档族架构.json"
      }
    ],
    "gate_rules": {
      "phase1_cross_validation": {
        "enabled": true
      },
      "phase2_schema_comparison": {
        "enabled": false
      },
      "phase3_anomaly_detection": {
        "enabled": false
      }
    },
    "inputs": [
      {
        "name": "需求文档",
        "path": "00-需求描述.md"
      },
      {
        "name": "引擎分析报告",
        "path": "outputs/引擎分析报告.json"
      },
      {
        "name": "审阅报告",
        "path": "outputs/审阅报告.json"
      },
      {
        "name": "对抗分析报告",
        "path": "outputs/文档红队-对抗分析报告.json"
      },
      {
        "name": "引擎文档族范式",
        "path": "knowledge/引擎文档族范式.md",
        "type": "knowledge"
      },
      {
        "name": "编排范式",
        "path": "knowledge/app.yaml编排范式.md",
        "type": "knowledge"
      },
      {
        "name": "文档族分层设计方法论",
        "path": "knowledge/文档族分层设计方法论.md",
        "type": "knowledge"
      }
    ],
    "input_groups": [
      [
        "引擎分析师"
      ],
      [
        "知识管理者"
      ],
      [
        "文档架构师"
      ]
    ],
    "verdicts": [
      "confirmed"
    ]
  },
  {
    "role_name": "文档撰写者",
    "skill_path": "roles/文档撰写者/skill.md",
    "blocking_mode": "auto",
    "outputs": [
      {
        "name": "文档族正文",
        "path": "文档族/"
      }
    ],
    "gate_rules": {
      "phase1_cross_validation": {
        "enabled": true
      },
      "phase2_schema_comparison": {
        "enabled": false
      },
      "phase3_anomaly_detection": {
        "enabled": false
      }
    },
    "inputs": [
      {
        "name": "需求文档",
        "path": "00-需求描述.md"
      },
      {
        "name": "引擎分析报告",
        "path": "outputs/引擎分析报告.json"
      },
      {
        "name": "文档族架构设计",
        "path": "outputs/文档族架构.json"
      },
      {
        "name": "审阅报告",
        "path": "outputs/审阅报告.json"
      },
      {
        "name": "对抗分析报告",
        "path": "outputs/文档红队-对抗分析报告.json"
      },
      {
        "name": "引擎文档族范式",
        "path": "knowledge/引擎文档族范式.md",
        "type": "knowledge"
      },
      {
        "name": "引擎特性提炼指南",
        "path": "knowledge/引擎特性提炼指南.md",
        "type": "knowledge"
      }
    ],
    "input_groups": [
      [
        "文档架构师"
      ],
      [
        "知识管理者"
      ],
      [
        "文档撰写者"
      ]
    ],
    "verdicts": [
      "confirmed"
    ]
  },
  {
    "role_name": "文档审阅者",
    "skill_path": "roles/文档审阅者/skill.md",
    "blocking_mode": "auto",
    "outputs": [
      {
        "name": "审阅报告",
        "path": "outputs/审阅报告.json"
      }
    ],
    "gate_rules": {
      "phase1_cross_validation": {
        "enabled": true
      },
      "phase2_schema_comparison": {
        "enabled": false
      },
      "phase3_anomaly_detection": {
        "enabled": false
      }
    },
    "inputs": [
      {
        "name": "需求文档",
        "path": "00-需求描述.md"
      },
      {
        "name": "引擎分析报告",
        "path": "outputs/引擎分析报告.json"
      },
      {
        "name": "文档族架构设计",
        "path": "outputs/文档族架构.json"
      },
      {
        "name": "文档族正文",
        "path": "文档族/"
      },
      {
        "name": "SDK规范",
        "path": "knowledge/SDK_SPEC.md",
        "type": "knowledge"
      },
      {
        "name": "文档审阅与对抗标准手册",
        "path": "knowledge/文档审阅与对抗标准手册.md",
        "type": "knowledge"
      }
    ],
    "input_groups": [
      [
        "文档撰写者"
      ],
      [
        "文档审阅者"
      ]
    ],
    "verdicts": [
      "confirmed"
    ]
  },
  {
    "role_name": "文档红队",
    "skill_path": "roles/文档红队/skill.md",
    "blocking_mode": "auto",
    "outputs": [
      {
        "name": "对抗分析报告",
        "path": "outputs/文档红队-对抗分析报告.json"
      }
    ],
    "gate_rules": {
      "phase1_cross_validation": {
        "enabled": true
      },
      "phase2_schema_comparison": {
        "enabled": false
      },
      "phase3_anomaly_detection": {
        "enabled": false
      }
    },
    "inputs": [
      {
        "name": "需求文档",
        "path": "00-需求描述.md"
      },
      {
        "name": "文档族正文",
        "path": "文档族/"
      },
      {
        "name": "SDK规范",
        "path": "knowledge/SDK_SPEC.md",
        "type": "knowledge"
      },
      {
        "name": "文档审阅与对抗标准手册",
        "path": "knowledge/文档审阅与对抗标准手册.md",
        "type": "knowledge"
      }
    ],
    "input_groups": [
      [
        "文档撰写者"
      ],
      [
        "文档红队"
      ]
    ],
    "verdicts": [
      "confirmed"
    ]
  },
  {
    "role_name": "优化分析师",
    "skill_path": "roles/优化分析师/skill.md",
    "blocking_mode": "auto",
    "outputs": [
      {
        "name": "优化建议清单",
        "path": "outputs/优化建议清单.json"
      }
    ],
    "gate_rules": {
      "phase1_cross_validation": {
        "enabled": true
      },
      "phase2_schema_comparison": {
        "enabled": false
      },
      "phase3_anomaly_detection": {
        "enabled": false
      }
    },
    "inputs": [
      {
        "name": "引擎分析报告",
        "path": "outputs/引擎分析报告.json"
      },
      {
        "name": "文档族正文",
        "path": "文档族/"
      },
      {
        "name": "SDK规范",
        "path": "knowledge/SDK_SPEC.md",
        "type": "knowledge"
      }
    ],
    "input_groups": [
      [
        "文档撰写者"
      ],
      [
        "优化分析师"
      ]
    ],
    "verdicts": [
      "confirmed"
    ]
  },
  {
    "role_name": "知识管理者",
    "skill_path": "roles/知识管理者/skill.md",
    "blocking_mode": "auto",
    "outputs": [
      {
        "name": "构建报告",
        "path": "构建报告.md"
      }
    ],
    "gate_rules": {
      "phase1_cross_validation": {
        "enabled": true
      },
      "phase2_schema_comparison": {
        "enabled": false
      },
      "phase3_anomaly_detection": {
        "enabled": false
      }
    },
    "inputs": [
      {
        "name": "需求文档",
        "path": "00-需求描述.md"
      },
      {
        "name": "引擎分析报告",
        "path": "outputs/引擎分析报告.json"
      },
      {
        "name": "文档族架构设计",
        "path": "outputs/文档族架构.json"
      },
      {
        "name": "文档族正文",
        "path": "文档族/"
      },
      {
        "name": "审阅报告",
        "path": "outputs/审阅报告.json"
      },
      {
        "name": "对抗分析报告",
        "path": "outputs/文档红队-对抗分析报告.json"
      },
      {
        "name": "优化建议清单",
        "path": "outputs/优化建议清单.json"
      }
    ],
    "input_groups": [
      [
        "文档审阅者",
        "文档红队",
        "优化分析师"
      ],
      [
        "知识管理者"
      ]
    ],
    "verdicts": [
      "confirmed",
      "loop",
      "major_rework"
    ]
  }
]